awa.cpython-311-darwin.so
awadb/__init__.py
awadb/awadb_api.py
awadb/library.py
awadb/punctuation_marks_en.py
awadb/stop_words_en.py
awadb/words_stem_en.py
awadb/awa_embedding/clipembedding.py
awadb/awa_embedding/huggingface.py
awadb/awa_embedding/openai.py
awadb/llm_embedding/__init__.py
awadb-0.3.13.dist-info/LICENSE
awadb-0.3.13.dist-info/METADATA
awadb-0.3.13.dist-info/WHEEL
awadb-0.3.13.dist-info/top_level.txt
awadb-0.3.13.dist-info/RECORD
