Metadata-Version: 2.1
Name: awadb
Version: 0.3.13
Summary: Local lightweight AI Native database for RAG, incluing embedding vectors and text search for LLM generation
Home-page: https://github.com/awa-ai/awadb
Author: Vincent
Author-email: awadb.vincent@gmail.com
License: Apache 2.0
Keywords: AI Native SearchEngine,RAG,Embedding vectors,Multi-model search
Requires-Python: >=3.7
License-File: LICENSE
Provides-Extra: test
Requires-Dist: pytest (>=6.0) ; extra == 'test'
